nmims/__init__.py
nmims/knowledge.py
nmims/knowledge_logic.py
nmims/knowledge_question.py
nmims/knowledge_theory.py
nmims/optimization.py
nmims/optimization_theory.py
nmims/search.py
nmims/search_bfs_dfs.py
nmims/search_gbfs_astar.py
nmims/search_theory.py
nmims/uncertainity_theory.py
nmims-0.0.1.dist-info/LICENSE
nmims-0.0.1.dist-info/METADATA
nmims-0.0.1.dist-info/WHEEL
nmims-0.0.1.dist-info/top_level.txt
nmims-0.0.1.dist-info/RECORD
