Metadata-Version: 2.1
Name: nmims
Version: 0.0.1
Summary: nmims
Author: kd_kk
Author-email: kdkk6161@gmail.com
Keywords: knowledge
Classifier: Development Status :: 1 - Planning
Classifier: Intended Audience :: Developers
Classifier: Programming Language :: Python :: 3
Classifier: Operating System :: Unix
Classifier: Operating System :: MacOS :: MacOS X
Classifier: Operating System :: Microsoft :: Windows
License-File: LICENSE
